memorization/__init__.py
memorization-0.0.1.dist-info/LICENSE
memorization-0.0.1.dist-info/METADATA
memorization-0.0.1.dist-info/WHEEL
memorization-0.0.1.dist-info/top_level.txt
memorization-0.0.1.dist-info/RECORD
