Metadata-Version: 2.1
Name: memorization
Version: 0.0.1
Summary: Memory
Home-page: https://github.com/ciela-io/memorization
Author: Modern LLC
Author-email: modernllc@outlook.com
License: UNKNOWN
Platform: UNKNOWN
Classifier: Programming Language :: Python :: 3
Classifier: License :: OSI Approved :: MIT License
Classifier: Operating System :: OS Independent
